[
  {
    "node_id":"Node1",
    "variable":"total_rainfall",
    "mean":38.0862745098,
    "median":16.8,
    "std":68.8105312277,
    "min":0.0,
    "max":373.1
  },
  {
    "node_id":"Node1",
    "variable":"rain_intensity",
    "mean":2.6865760166,
    "median":1.4,
    "std":3.2803708297,
    "min":0.0,
    "max":15.6
  },
  {
    "node_id":"Node1",
    "variable":"cumulative_total_rainfall",
    "mean":268.6568627451,
    "median":146.3,
    "std":315.707822681,
    "min":0.5,
    "max":950.6
  },
  {
    "node_id":"Node1",
    "variable":"canal_water_level",
    "mean":20.3672501424,
    "median":18.3965012688,
    "std":18.2982960113,
    "min":1.5,
    "max":50.5427302004
  },
  {
    "node_id":"Node2",
    "variable":"total_rainfall",
    "mean":156.4176470588,
    "median":44.1,
    "std":359.7566386911,
    "min":0.0,
    "max":2358.3
  },
  {
    "node_id":"Node2",
    "variable":"rain_intensity",
    "mean":5.8202932148,
    "median":2.7,
    "std":8.45073489,
    "min":0.0,
    "max":44.6727272727
  },
  {
    "node_id":"Node2",
    "variable":"cumulative_total_rainfall",
    "mean":1196.2470588235,
    "median":417.2,
    "std":1651.7416086486,
    "min":0.7,
    "max":4792.9
  },
  {
    "node_id":"Node2",
    "variable":"canal_water_level",
    "mean":25.9711528473,
    "median":22.4176942823,
    "std":14.3160473142,
    "min":10.5,
    "max":53.3759882314
  }
]