[
  {
    "selected_event_id":2,
    "original_shared_event_id":11,
    "node_id":"Node1",
    "timestamp":"2026-02-14 09:00:00",
    "plot_start":"2026-02-14 09:00:00",
    "plot_end":"2026-02-15 05:00:00",
    "event_start":"2026-02-14 15:00:00",
    "event_end":"2026-02-14 17:00:00",
    "event_duration_hours":3.0,
    "is_selected_event_window":false,
    "total_rainfall":0.0,
    "rain_intensity":0.0,
    "canal_water_level":44.7363636364,
    "canal_water_level_change":0.0
  },
  {
    "selected_event_id":2,
    "original_shared_event_id":11,
    "node_id":"Node1",
    "timestamp":"2026-02-14 10:00:00",
    "plot_start":"2026-02-14 09:00:00",
    "plot_end":"2026-02-15 05:00:00",
    "event_start":"2026-02-14 15:00:00",
    "event_end":"2026-02-14 17:00:00",
    "event_duration_hours":3.0,
    "is_selected_event_window":false,
    "total_rainfall":0.0,
    "rain_intensity":0.0,
    "canal_water_level":44.7363636364,
    "canal_water_level_change":0.0
  },
  {
    "selected_event_id":2,
    "original_shared_event_id":11,
    "node_id":"Node1",
    "timestamp":"2026-02-14 11:00:00",
    "plot_start":"2026-02-14 09:00:00",
    "plot_end":"2026-02-15 05:00:00",
    "event_start":"2026-02-14 15:00:00",
    "event_end":"2026-02-14 17:00:00",
    "event_duration_hours":3.0,
    "is_selected_event_window":false,
    "total_rainfall":0.0,
    "rain_intensity":0.0,
    "canal_water_level":44.7363636364,
    "canal_water_level_change":0.0
  },
  {
    "selected_event_id":2,
    "original_shared_event_id":11,
    "node_id":"Node1",
    "timestamp":"2026-02-14 12:00:00",
    "plot_start":"2026-02-14 09:00:00",
    "plot_end":"2026-02-15 05:00:00",
    "event_start":"2026-02-14 15:00:00",
    "event_end":"2026-02-14 17:00:00",
    "event_duration_hours":3.0,
    "is_selected_event_window":false,
    "total_rainfall":0.0,
    "rain_intensity":0.0,
    "canal_water_level":44.7363636364,
    "canal_water_level_change":0.0
  },
  {
    "selected_event_id":2,
    "original_shared_event_id":11,
    "node_id":"Node1",
    "timestamp":"2026-02-14 13:00:00",
    "plot_start":"2026-02-14 09:00:00",
    "plot_end":"2026-02-15 05:00:00",
    "event_start":"2026-02-14 15:00:00",
    "event_end":"2026-02-14 17:00:00",
    "event_duration_hours":3.0,
    "is_selected_event_window":false,
    "total_rainfall":0.0,
    "rain_intensity":0.0,
    "canal_water_level":44.7363636364,
    "canal_water_level_change":0.0
  },
  {
    "selected_event_id":2,
    "original_shared_event_id":11,
    "node_id":"Node1",
    "timestamp":"2026-02-14 14:00:00",
    "plot_start":"2026-02-14 09:00:00",
    "plot_end":"2026-02-15 05:00:00",
    "event_start":"2026-02-14 15:00:00",
    "event_end":"2026-02-14 17:00:00",
    "event_duration_hours":3.0,
    "is_selected_event_window":false,
    "total_rainfall":0.0,
    "rain_intensity":0.0,
    "canal_water_level":44.7363636364,
    "canal_water_level_change":0.0
  },
  {
    "selected_event_id":2,
    "original_shared_event_id":11,
    "node_id":"Node1",
    "timestamp":"2026-02-14 15:00:00",
    "plot_start":"2026-02-14 09:00:00",
    "plot_end":"2026-02-15 05:00:00",
    "event_start":"2026-02-14 15:00:00",
    "event_end":"2026-02-14 17:00:00",
    "event_duration_hours":3.0,
    "is_selected_event_window":true,
    "total_rainfall":3.5,
    "rain_intensity":1.8,
    "canal_water_level":46.1142857143,
    "canal_water_level_change":1.3779220779
  },
  {
    "selected_event_id":2,
    "original_shared_event_id":11,
    "node_id":"Node1",
    "timestamp":"2026-02-14 16:00:00",
    "plot_start":"2026-02-14 09:00:00",
    "plot_end":"2026-02-15 05:00:00",
    "event_start":"2026-02-14 15:00:00",
    "event_end":"2026-02-14 17:00:00",
    "event_duration_hours":3.0,
    "is_selected_event_window":true,
    "total_rainfall":60.2,
    "rain_intensity":7.5,
    "canal_water_level":45.95,
    "canal_water_level_change":-0.1642857143
  },
  {
    "selected_event_id":2,
    "original_shared_event_id":11,
    "node_id":"Node1",
    "timestamp":"2026-02-14 17:00:00",
    "plot_start":"2026-02-14 09:00:00",
    "plot_end":"2026-02-15 05:00:00",
    "event_start":"2026-02-14 15:00:00",
    "event_end":"2026-02-14 17:00:00",
    "event_duration_hours":3.0,
    "is_selected_event_window":true,
    "total_rainfall":54.6,
    "rain_intensity":6.3,
    "canal_water_level":46.3,
    "canal_water_level_change":0.35
  },
  {
    "selected_event_id":2,
    "original_shared_event_id":11,
    "node_id":"Node1",
    "timestamp":"2026-02-14 18:00:00",
    "plot_start":"2026-02-14 09:00:00",
    "plot_end":"2026-02-15 05:00:00",
    "event_start":"2026-02-14 15:00:00",
    "event_end":"2026-02-14 17:00:00",
    "event_duration_hours":3.0,
    "is_selected_event_window":false,
    "total_rainfall":0.0,
    "rain_intensity":0.0,
    "canal_water_level":46.3,
    "canal_water_level_change":0.0
  },
  {
    "selected_event_id":2,
    "original_shared_event_id":11,
    "node_id":"Node1",
    "timestamp":"2026-02-14 19:00:00",
    "plot_start":"2026-02-14 09:00:00",
    "plot_end":"2026-02-15 05:00:00",
    "event_start":"2026-02-14 15:00:00",
    "event_end":"2026-02-14 17:00:00",
    "event_duration_hours":3.0,
    "is_selected_event_window":false,
    "total_rainfall":0.0,
    "rain_intensity":0.0,
    "canal_water_level":46.3,
    "canal_water_level_change":0.0
  },
  {
    "selected_event_id":2,
    "original_shared_event_id":11,
    "node_id":"Node1",
    "timestamp":"2026-02-14 20:00:00",
    "plot_start":"2026-02-14 09:00:00",
    "plot_end":"2026-02-15 05:00:00",
    "event_start":"2026-02-14 15:00:00",
    "event_end":"2026-02-14 17:00:00",
    "event_duration_hours":3.0,
    "is_selected_event_window":false,
    "total_rainfall":0.0,
    "rain_intensity":0.0,
    "canal_water_level":46.3,
    "canal_water_level_change":0.0
  },
  {
    "selected_event_id":2,
    "original_shared_event_id":11,
    "node_id":"Node1",
    "timestamp":"2026-02-14 21:00:00",
    "plot_start":"2026-02-14 09:00:00",
    "plot_end":"2026-02-15 05:00:00",
    "event_start":"2026-02-14 15:00:00",
    "event_end":"2026-02-14 17:00:00",
    "event_duration_hours":3.0,
    "is_selected_event_window":false,
    "total_rainfall":0.0,
    "rain_intensity":0.0,
    "canal_water_level":46.3,
    "canal_water_level_change":0.0
  },
  {
    "selected_event_id":2,
    "original_shared_event_id":11,
    "node_id":"Node1",
    "timestamp":"2026-02-14 22:00:00",
    "plot_start":"2026-02-14 09:00:00",
    "plot_end":"2026-02-15 05:00:00",
    "event_start":"2026-02-14 15:00:00",
    "event_end":"2026-02-14 17:00:00",
    "event_duration_hours":3.0,
    "is_selected_event_window":false,
    "total_rainfall":0.0,
    "rain_intensity":0.0,
    "canal_water_level":46.3,
    "canal_water_level_change":0.0
  },
  {
    "selected_event_id":2,
    "original_shared_event_id":11,
    "node_id":"Node1",
    "timestamp":"2026-02-14 23:00:00",
    "plot_start":"2026-02-14 09:00:00",
    "plot_end":"2026-02-15 05:00:00",
    "event_start":"2026-02-14 15:00:00",
    "event_end":"2026-02-14 17:00:00",
    "event_duration_hours":3.0,
    "is_selected_event_window":false,
    "total_rainfall":0.0,
    "rain_intensity":0.0,
    "canal_water_level":46.3,
    "canal_water_level_change":0.0
  },
  {
    "selected_event_id":2,
    "original_shared_event_id":11,
    "node_id":"Node1",
    "timestamp":"2026-02-15 00:00:00",
    "plot_start":"2026-02-14 09:00:00",
    "plot_end":"2026-02-15 05:00:00",
    "event_start":"2026-02-14 15:00:00",
    "event_end":"2026-02-14 17:00:00",
    "event_duration_hours":3.0,
    "is_selected_event_window":false,
    "total_rainfall":0.0,
    "rain_intensity":0.0,
    "canal_water_level":46.3,
    "canal_water_level_change":0.0
  },
  {
    "selected_event_id":2,
    "original_shared_event_id":11,
    "node_id":"Node1",
    "timestamp":"2026-02-15 01:00:00",
    "plot_start":"2026-02-14 09:00:00",
    "plot_end":"2026-02-15 05:00:00",
    "event_start":"2026-02-14 15:00:00",
    "event_end":"2026-02-14 17:00:00",
    "event_duration_hours":3.0,
    "is_selected_event_window":false,
    "total_rainfall":0.0,
    "rain_intensity":0.0,
    "canal_water_level":46.3,
    "canal_water_level_change":0.0
  },
  {
    "selected_event_id":2,
    "original_shared_event_id":11,
    "node_id":"Node1",
    "timestamp":"2026-02-15 02:00:00",
    "plot_start":"2026-02-14 09:00:00",
    "plot_end":"2026-02-15 05:00:00",
    "event_start":"2026-02-14 15:00:00",
    "event_end":"2026-02-14 17:00:00",
    "event_duration_hours":3.0,
    "is_selected_event_window":false,
    "total_rainfall":0.0,
    "rain_intensity":0.0,
    "canal_water_level":46.3,
    "canal_water_level_change":0.0
  },
  {
    "selected_event_id":2,
    "original_shared_event_id":11,
    "node_id":"Node1",
    "timestamp":"2026-02-15 03:00:00",
    "plot_start":"2026-02-14 09:00:00",
    "plot_end":"2026-02-15 05:00:00",
    "event_start":"2026-02-14 15:00:00",
    "event_end":"2026-02-14 17:00:00",
    "event_duration_hours":3.0,
    "is_selected_event_window":false,
    "total_rainfall":0.0,
    "rain_intensity":0.0,
    "canal_water_level":46.3,
    "canal_water_level_change":0.0
  },
  {
    "selected_event_id":2,
    "original_shared_event_id":11,
    "node_id":"Node1",
    "timestamp":"2026-02-15 04:00:00",
    "plot_start":"2026-02-14 09:00:00",
    "plot_end":"2026-02-15 05:00:00",
    "event_start":"2026-02-14 15:00:00",
    "event_end":"2026-02-14 17:00:00",
    "event_duration_hours":3.0,
    "is_selected_event_window":false,
    "total_rainfall":0.0,
    "rain_intensity":0.0,
    "canal_water_level":46.3,
    "canal_water_level_change":0.0
  },
  {
    "selected_event_id":2,
    "original_shared_event_id":11,
    "node_id":"Node1",
    "timestamp":"2026-02-15 05:00:00",
    "plot_start":"2026-02-14 09:00:00",
    "plot_end":"2026-02-15 05:00:00",
    "event_start":"2026-02-14 15:00:00",
    "event_end":"2026-02-14 17:00:00",
    "event_duration_hours":3.0,
    "is_selected_event_window":false,
    "total_rainfall":0.0,
    "rain_intensity":0.0,
    "canal_water_level":46.3,
    "canal_water_level_change":0.0
  }
]